[
  {
    "category": "HISTORY",
    "air_date": "2004-12-31",
    "question": "'For the last 8 years of his life, Galileo was under house arrest for espousing this man's theory'",
    "value": "$200",
    "answer": "Copernicus",
    "round": "Jeopardy!",
    "show_number": "4680"
  },
  {
    "category": "ESPN's TOP 10 ALL-TIME ATHLETES",
    "air_date": "2004-12-31",
    "question": "'No. 2: 1912 Olympian; football star at Carlisle Indian School; 6 MLB seasons with the Reds, Giants & Braves'",
    "value": "$200",
    "answer": "Jim Thorpe",
    "round": "Jeopardy!",
    "show_number": "4680"
  },
  {
    "category": "EVERYBODY TALKS ABOUT IT...",
    "air_date": "2004-12-31",
    "question": "'The city of Yuma in this state has a record average of 4,055 hours of sunshine each year'",
    "value": "$200",
    "answer": "Arizona",
    "round": "Jeopardy!",
    "show_number": "4680"
  },
  {
    "category": "THE COMPANY LINE",
    "air_date": "2004-12-31",
    "question": "'In 1963, live on \"The Art Linkletter Show\", this company served its billionth burger'",
    "value": "$200",
    "answer": "McDonald\\'s",
    "round": "Jeopardy!",
    "show_number": "4680"
  },
  {
    "category": "EPITAPHS & TRIBUTES",
    "air_date": "2004-12-31",
    "question": "'Signer of the Dec. of Indep., framer of the Constitution of Mass., second President of the United States'",
    "value": "$200",
    "answer": "John Adams",
    "round": "Jeopardy!",
    "show_number": "4680"
  },
  {
    "category": "3-LETTER WORDS",
    "air_date": "2004-12-31",
    "question": "'In the title of an Aesop fable, this insect shared billing with a grasshopper'",
    "value": "$200",
    "answer": "the ant",
    "round": "Jeopardy!",
    "show_number": "4680"
  },
  {
    "category": "HISTORY",
    "air_date": "2004-12-31",
    "question": "'Built in 312 B.C. to link Rome & the South of Italy, it's still in use today'",
    "value": "$400",
    "answer": "the Appian Way",
    "round": "Jeopardy!",
    "show_number": "4680"
  },
  {
    "category": "ESPN's TOP 10 ALL-TIME ATHLETES",
    "air_date": "2004-12-31",
    "question": "'No. 8: 30 steals for the Birmingham Barons; 2,306 steals for the Bulls'",
    "value": "$400",
    "answer": "Michael Jordan",
    "round": "Jeopardy!",
    "show_number": "4680"
  },
  {
    "category": "EVERYBODY TALKS ABOUT IT...",
    "air_date": "2004-12-31",
    "question": "'In the winter of 1971-72, a record 1,122 inches of snow fell at Rainier Paradise Ranger Station in this state'",
    "value": "$400",
    "answer": "Washington",
    "round": "Jeopardy!",
    "show_number": "4680"
  },
  {
    "category": "THE COMPANY LINE",
    "air_date": "2004-12-31",
    "question": "'This housewares store was named for the packaging its merchandise came in & was first displayed on'",
    "value": "$400",
    "answer": "Crate & Barrel",
    "round": "Jeopardy!",
    "show_number": "4680"
  },
  {
    "category": "EPITAPHS & TRIBUTES",
    "air_date": "2004-12-31",
    "question": "'\"And away we go\"'",
    "value": "$400",
    "answer": "Jackie Gleason",
    "round": "Jeopardy!",
    "show_number": "4680"
  },
  {
    "category": "3-LETTER WORDS",
    "air_date": "2004-12-31",
    "question": "'Cows regurgitate this from the first stomach to the mouth & chew it again'",
    "value": "$400",
    "answer": "the cud",
    "round": "Jeopardy!",
    "show_number": "4680"
  },
  {
    "category": "HISTORY",
    "air_date": "2004-12-31",
    "question": "'In 1000 Rajaraja I of the Cholas battled to take this Indian Ocean island now known for its tea'",
    "value": "$600",
    "answer": "Ceylon (or Sri Lanka)",
    "round": "Jeopardy!",
    "show_number": "4680"
  },
  {
    "category": "ESPN's TOP 10 ALL-TIME ATHLETES",
    "air_date": "2004-12-31",
    "question": "'No. 1: Lettered in hoops, football & lacrosse at Syracuse & if you think he couldn't act, ask his 11 \"unclean\" buddies'",
    "value": "$600",
    "answer": "Jim Brown",
    "round": "Jeopardy!",
    "show_number": "4680"
  },
  {
    "category": "EVERYBODY TALKS ABOUT IT...",
    "air_date": "2004-12-31",
    "question": "'On June 28, 1994 the nat'l weather service began issuing this index that rates the intensity of the sun's radiation'",
    "value": "$600",
    "answer": "the UV index",
    "round": "Jeopardy!",
    "show_number": "4680"
  },
  {
    "category": "THE COMPANY LINE",
    "air_date": "2004-12-31",
    "question": "'This company's Accutron watch, introduced in 1960, had a guarantee of accuracy to within one minute a  month'",
    "value": "$600",
    "answer": "Bulova",
    "round": "Jeopardy!",
    "show_number": "4680"
  },
  {
    "category": "EPITAPHS & TRIBUTES",
    "air_date": "2004-12-31",
    "question": "'Outlaw: \"Murdered by a traitor and a coward whose name is not worthy to appear here\"'",
    "value": "$600",
    "answer": "Jesse James",
    "round": "Jeopardy!",
    "show_number": "4680"
  },
  {
    "category": "3-LETTER WORDS",
    "air_date": "2004-12-31",
    "question": "'A small demon, or a mischievous child (who might be a little demon!)'",
    "value": "$600",
    "answer": "imp",
    "round": "Jeopardy!",
    "show_number": "4680"
  },
  {
    "category": "HISTORY",
    "air_date": "2004-12-31",
    "question": "'Karl led the first of these Marxist organizational efforts; the second one began in 1889'",
    "value": "$800",
    "answer": "the International",
    "round": "Jeopardy!",
    "show_number": "4680"
  },
  {
    "category": "ESPN's TOP 10 ALL-TIME ATHLETES",
    "air_date": "2004-12-31",
    "question": "'No. 10: FB/LB for Columbia U. in the 1920s; MVP for the Yankees in '27 & '36; \"Gibraltar in Cleats\"'",
    "value": "$800",
    "answer": "(Lou) Gehrig",
    "round": "Jeopardy!",
    "show_number": "4680"
  },
  {
    "category": "EVERYBODY TALKS ABOUT IT...",
    "air_date": "2004-12-31",
    "question": "'Africa's lowest temperature was 11 degrees below zero in 1935 at Ifrane, just south of Fez in this country'",
    "value": "$800",
    "answer": "Morocco",
    "round": "Jeopardy!",
    "show_number": "4680"
  },
  {
    "category": "THE COMPANY LINE",
    "air_date": "2004-12-31",
    "question": "'Edward Teller & this man partnered in 1898 to sell high fashions to women'",
    "value": "$800",
    "answer": "(Paul) Bonwit",
    "round": "Jeopardy!",
    "show_number": "4680"
  },
  {
    "category": "EPITAPHS & TRIBUTES",
    "air_date": "2004-12-31",
    "question": "'1939 Oscar winner: \"...you are a credit to your craft, your race and to your family\"'",
    "value": "$2,000",
    "answer": "Hattie McDaniel (for her role in Gone with the Wind)",
    "round": "Jeopardy!",
    "show_number": "4680"
  },
  {
    "category": "3-LETTER WORDS",
    "air_date": "2004-12-31",
    "question": "'In geologic time one of these, shorter than an eon, is divided into periods & subdivided into epochs'",
    "value": "$800",
    "answer": "era",
    "round": "Jeopardy!",
    "show_number": "4680"
  },
  {
    "category": "HISTORY",
    "air_date": "2004-12-31",
    "question": "'This Asian political party was founded in 1885 with \"Indian National\" as part of its name'",
    "value": "$1000",
    "answer": "the Congress Party",
    "round": "Jeopardy!",
    "show_number": "4680"
  },
  {
    "category": "ESPN's TOP 10 ALL-TIME ATHLETES",
    "air_date": "2004-12-31",
    "question": "'No. 5: Only center to lead the NBA in assists; track scholarship to Kansas U.; marathoner; volleyballer'",
    "value": "$1000",
    "answer": "(Wilt) Chamberlain",
    "round": "Jeopardy!",
    "show_number": "4680"
  },
  {
    "category": "THE COMPANY LINE",
    "air_date": "2004-12-31",
    "question": "'The Kirschner brothers, Don & Bill, named this ski company for themselves & the second-highest mountain'",
    "value": "$1000",
    "answer": "K2",
    "round": "Jeopardy!",
    "show_number": "4680"
  },
  {
    "category": "EPITAPHS & TRIBUTES",
    "air_date": "2004-12-31",
    "question": "'Revolutionary War hero: \"His spirit is in Vermont now\"'",
    "value": "$1000",
    "answer": "Ethan Allen",
    "round": "Jeopardy!",
    "show_number": "4680"
  },
  {
    "category": "3-LETTER WORDS",
    "air_date": "2004-12-31",
    "question": "'A single layer of paper, or to perform one's craft diligently'",
    "value": "$1000",
    "answer": "ply",
    "round": "Jeopardy!",
    "show_number": "4680"
  },
  {
    "category": "DR. SEUSS AT THE MULTIPLEX",
    "air_date": "2004-12-31",
    "question": "'<a href=\"http://www.j-archive.com/media/2004-12-31_DJ_23.mp3\">Beyond ovoid abandonment, beyond ovoid betrayal... you won't believe the ending when he \"Hatches the Egg\"</a>'",
    "value": "$400",
    "answer": "Horton",
    "round": "Double Jeopardy!",
    "show_number": "4680"
  },
  {
    "category": "PRESIDENTIAL STATES OF BIRTH",
    "air_date": "2004-12-31",
    "question": "'California'",
    "value": "$400",
    "answer": "Nixon",
    "round": "Double Jeopardy!",
    "show_number": "4680"
  },
  {
    "category": "AIRLINE TRAVEL",
    "air_date": "2004-12-31",
    "question": "'It can be a place to leave your puppy when you take a trip, or a carrier for him that fits under an airplane seat'",
    "value": "$400",
    "answer": "a kennel",
    "round": "Double Jeopardy!",
    "show_number": "4680"
  },
  {
    "category": "THAT OLD-TIME RELIGION",
    "air_date": "2004-12-31",
    "question": "'He's considered the author of the Pentateuch, which is hard to believe, as Deuteronomy continues after his death'",
    "value": "$400",
    "answer": "Moses",
    "round": "Double Jeopardy!",
    "show_number": "4680"
  },
  {
    "category": "MUSICAL TRAINS",
    "air_date": "2004-12-31",
    "question": "'Steven Tyler of this band lent his steamin' vocals to \"Train Kept A-Rollin'\", first popularized by the Yardbirds'",
    "value": "$400",
    "answer": "Aerosmith",
    "round": "Double Jeopardy!",
    "show_number": "4680"
  },
  {
    "category": "\"X\"s & \"O\"s",
    "air_date": "2004-12-31",
    "question": "'Around 100 A.D. Tacitus wrote a book on how this art of persuasive speaking had declined since Cicero'",
    "value": "$400",
    "answer": "oratory",
    "round": "Double Jeopardy!",
    "show_number": "4680"
  },
  {
    "category": "PRESIDENTIAL STATES OF BIRTH",
    "air_date": "2004-12-31",
    "question": "'1 of the 2 born in Vermont'",
    "value": "$800",
    "answer": "Coolidge (or Chester Arthur)",
    "round": "Double Jeopardy!",
    "show_number": "4680"
  },
  {
    "category": "AIRLINE TRAVEL",
    "air_date": "2004-12-31",
    "question": "'When it began on Pan Am & Qantas in the late '70s, it was basically a roped-off part of the economy cabin with free drinks'",
    "value": "$800",
    "answer": "business class",
    "round": "Double Jeopardy!",
    "show_number": "4680"
  },
  {
    "category": "THAT OLD-TIME RELIGION",
    "air_date": "2004-12-31",
    "question": "'Ali, who married this man's daughter Fatima, is considered by Shia Muslims to be his true successor'",
    "value": "$800",
    "answer": "Muhammed",
    "round": "Double Jeopardy!",
    "show_number": "4680"
  },
  {
    "category": "MUSICAL TRAINS",
    "air_date": "2004-12-31",
    "question": "'During the 1954-1955 Sun sessions, Elvis climbed aboard this train \"sixteen coaches long\"'",
    "value": "$800",
    "answer": "the \"Mystery Train\"",
    "round": "Double Jeopardy!",
    "show_number": "4680"
  },
  {
    "category": "\"X\"s & \"O\"s",
    "air_date": "2004-12-31",
    "question": "'The shorter glass seen <a href=\"http://www.j-archive.com/media/2004-12-31_DJ_12.jpg\" target=\"_blank\">here</a>, or a quaint cocktail made with sugar & bitters'",
    "value": "$800",
    "answer": "an old-fashioned",
    "round": "Double Jeopardy!",
    "show_number": "4680"
  },
  {
    "category": "DR. SEUSS AT THE MULTIPLEX",
    "air_date": "2004-12-31",
    "question": "'<a href=\"http://www.j-archive.com/media/2004-12-31_DJ_26.mp3\">Ripped from today's headlines, he was a turtle king gone mad; Mack was the one good turtle who'd bring him down</a>'",
    "value": "$1200",
    "answer": "Yertle",
    "round": "Double Jeopardy!",
    "show_number": "4680"
  },
  {
    "category": "AIRLINE TRAVEL",
    "air_date": "2004-12-31",
    "question": "'In 2003 this airline agreed to buy KLM, creating Europe's largest airline'",
    "value": "$2,000",
    "answer": "Air France",
    "round": "Double Jeopardy!",
    "show_number": "4680"
  },
  {
    "category": "THAT OLD-TIME RELIGION",
    "air_date": "2004-12-31",
    "question": "'Philadelphia got its start as a colony for this religious group of which William Penn was a member'",
    "value": "$1200",
    "answer": "the Quakers",
    "round": "Double Jeopardy!",
    "show_number": "4680"
  },
  {
    "category": "MUSICAL TRAINS",
    "air_date": "2004-12-31",
    "question": "'This \"Modern Girl\" first hit the Billboard Top 10 with \"Morning Train (Nine To Five)\"'",
    "value": "$1200",
    "answer": "(Sheena) Easton",
    "round": "Double Jeopardy!",
    "show_number": "4680"
  },
  {
    "category": "\"X\"s & \"O\"s",
    "air_date": "2004-12-31",
    "question": "'This stiff silken fabric is favored for bridal gowns, like Christina Applegate's in 2001'",
    "value": "$1200",
    "answer": "organza",
    "round": "Double Jeopardy!",
    "show_number": "4680"
  },
  {
    "category": "DR. SEUSS AT THE MULTIPLEX",
    "air_date": "2004-12-31",
    "question": "'<a href=\"http://www.j-archive.com/media/2004-12-31_DJ_25.mp3\">Somewhere between truth & fiction lies Marco's reality... on Halloween, you won't believe you saw it on this St.</a>'",
    "value": "$1600",
    "answer": "Mulberry Street",
    "round": "Double Jeopardy!",
    "show_number": "4680"
  },
  {
    "category": "AIRLINE TRAVEL",
    "air_date": "2004-12-31",
    "question": "'In 2004 United launched this new service that features low fares & more seats per plane'",
    "value": "$1600",
    "answer": "Ted",
    "round": "Double Jeopardy!",
    "show_number": "4680"
  },
  {
    "category": "THAT OLD-TIME RELIGION",
    "air_date": "2004-12-31",
    "question": "'With Mary I's accession in 1553 he ran to Geneva; he returned in 1559 & reformed the Church of Scotland'",
    "value": "$1600",
    "answer": "(John) Knox",
    "round": "Double Jeopardy!",
    "show_number": "4680"
  },
  {
    "category": "MUSICAL TRAINS",
    "air_date": "2004-12-31",
    "question": "'This band's \"Train In Vain\" was a hidden track on its original 1979 \"London Calling\" album'",
    "value": "$1600",
    "answer": "The Clash",
    "round": "Double Jeopardy!",
    "show_number": "4680"
  },
  {
    "category": "\"X\"s & \"O\"s",
    "air_date": "2004-12-31",
    "question": "'Cross-country skiing is sometimes referred to by these 2 letters, the same ones used to denote 90 in Roman numerals'",
    "value": "$1600",
    "answer": "XC",
    "round": "Double Jeopardy!",
    "show_number": "4680"
  },
  {
    "category": "DR. SEUSS AT THE MULTIPLEX",
    "air_date": "2004-12-31",
    "question": "'<a href=\"http://www.j-archive.com/media/2004-12-31_DJ_24.mp3\">\"500 Hats\"... 500 ways to die.  On July 4th, this young boy will defy a king... & become a legend</a>'",
    "value": "$2000",
    "answer": "Bartholomew Cubbins",
    "round": "Double Jeopardy!",
    "show_number": "4680"
  },
  {
    "category": "AIRLINE TRAVEL",
    "air_date": "2004-12-31",
    "question": "'In the seat pocket you'll find the catalog called \"Sky\" this, with must-haves like a solar-powered patio umbrella'",
    "value": "$2000",
    "answer": "Mall",
    "round": "Double Jeopardy!",
    "show_number": "4680"
  },
  {
    "category": "THAT OLD-TIME RELIGION",
    "air_date": "2004-12-31",
    "question": "'In 1534 he & his buddy Francis Xavier founded the Society of Jesus'",
    "value": "$3,200",
    "answer": "(St. Ignatius) Loyola",
    "round": "Double Jeopardy!",
    "show_number": "4680"
  },
  {
    "category": "MUSICAL TRAINS",
    "air_date": "2004-12-31",
    "question": "'In 1961 James Brown announced \"all aboard\" for this train'",
    "value": "$2000",
    "answer": "\"Night Train\"",
    "round": "Double Jeopardy!",
    "show_number": "4680"
  },
  {
    "category": "\"X\"s & \"O\"s",
    "air_date": "2004-12-31",
    "question": "'This 1797 imbroglio began when 3 French agents demanded a huge bribe from U.S. diplomats'",
    "value": "$2000",
    "answer": "the XYZ Affair",
    "round": "Double Jeopardy!",
    "show_number": "4680"
  },
  {
    "category": "THE SOLAR SYSTEM",
    "air_date": "2004-12-31",
    "question": "'Objects that pass closer to the sun than Mercury have been named for this mythological figure'",
    "value": null,
    "answer": "Icarus",
    "round": "Final Jeopardy!",
    "show_number": "4680"
  },
  {
    "category": "GEOGRAPHY \"E\"",
    "air_date": "2010-07-06",
    "question": "'It's the largest kingdom in the United Kingdom'",
    "value": "$200",
    "answer": "England",
    "round": "Jeopardy!",
    "show_number": "5957"
  },
  {
    "category": "RADIO DISNEY",
    "air_date": "2010-07-06",
    "question": "'\"Party In The U.S.A.\" is by this singer who also plays a young lady named Hannah'",
    "value": "$200",
    "answer": "Miley Cyrus",
    "round": "Jeopardy!",
    "show_number": "5957"
  },
  {
    "category": "PARTS OF PEACH",
    "air_date": "2010-07-06",
    "question": "'If this part of a peach is downy or fuzzy, the fruit's called a peach; if it's smooth, a nectarine'",
    "value": "$200",
    "answer": "the skin",
    "round": "Jeopardy!",
    "show_number": "5957"
  },
  {
    "category": "BE FRUITFUL & MULTIPLY",
    "air_date": "2010-07-06",
    "question": "'4 x 12'",
    "value": "$200",
    "answer": "48",
    "round": "Jeopardy!",
    "show_number": "5957"
  },
  {
    "category": "LET'S BOUNCE",
    "air_date": "2010-07-06",
    "question": "'This verb for bouncing a basketball sounds like you're slobbering'",
    "value": "$200",
    "answer": "dribbling",
    "round": "Jeopardy!",
    "show_number": "5957"
  },
  {
    "category": "RHYMES WITH SMART",
    "air_date": "2010-07-06",
    "question": "'Blood pumper'",
    "value": "$200",
    "answer": "heart",
    "round": "Jeopardy!",
    "show_number": "5957"
  },
  {
    "category": "GEOGRAPHY \"E\"",
    "air_date": "2010-07-06",
    "question": "'(<a href=\"http://www.j-archive.com/media/2010-07-06_J_22.wmv\">Tate: I'm Tate Shaffer aboard the <i>National Geographic Endeavour</i>.  Alex: And...</a>)  We're here in the Galapagos Islands at zero degrees latitude, which means we're right above this imaginary line that goes all the way around the Earth'",
    "value": "$400",
    "answer": "the equator",
    "round": "Jeopardy!",
    "show_number": "5957"
  },
  {
    "category": "RADIO DISNEY",
    "air_date": "2010-07-06",
    "question": "'\"Everybody Else\" knows these huggable toys precede \"On Fire\" in the name of a Radio Disney top 30 band; do you?'",
    "value": "$400",
    "answer": "Care Bears",
    "round": "Jeopardy!",
    "show_number": "5957"
  },
  {
    "category": "PARTS OF PEACH",
    "air_date": "2010-07-06",
    "question": "'Peaches are more than 80% this compound'",
    "value": "$400",
    "answer": "H2O",
    "round": "Jeopardy!",
    "show_number": "5957"
  },
  {
    "category": "BE FRUITFUL & MULTIPLY",
    "air_date": "2010-07-06",
    "question": "'7 x 7 x 2'",
    "value": "$400",
    "answer": "98",
    "round": "Jeopardy!",
    "show_number": "5957"
  },
  {
    "category": "LET'S BOUNCE",
    "air_date": "2010-07-06",
    "question": "'Sound navigation& ranging is the full name for this device that bounces radio waves underwater'",
    "value": "$400",
    "answer": "sonar",
    "round": "Jeopardy!",
    "show_number": "5957"
  },
  {
    "category": "RHYMES WITH SMART",
    "air_date": "2010-07-06",
    "question": "'Small, slender missile thrown at a board in a game'",
    "value": "$400",
    "answer": "a dart",
    "round": "Jeopardy!",
    "show_number": "5957"
  },
  {
    "category": "GEOGRAPHY \"E\"",
    "air_date": "2010-07-06",
    "question": "'This island in the South Pacific is named for the day of its discovery, a religious holiday'",
    "value": "$600",
    "answer": "Easter Island",
    "round": "Jeopardy!",
    "show_number": "5957"
  },
  {
    "category": "RADIO DISNEY",
    "air_date": "2010-07-06",
    "question": "'\"The songs on 'Under My Skin' are...deeper than those on 'Let Go'\" said this Canadian on Radio Disney's website'",
    "value": "$600",
    "answer": "Avril Lavigne",
    "round": "Jeopardy!",
    "show_number": "5957"
  },
  {
    "category": "PARTS OF PEACH",
    "air_date": "2010-07-06",
    "question": "'5-letter word for the hard interior of a peach'",
    "value": "$600",
    "answer": "the stone",
    "round": "Jeopardy!",
    "show_number": "5957"
  },
  {
    "category": "BE FRUITFUL & MULTIPLY",
    "air_date": "2010-07-06",
    "question": "'3 x 4 x 5 x 6'",
    "value": "$600",
    "answer": "360",
    "round": "Jeopardy!",
    "show_number": "5957"
  },
  {
    "category": "LET'S BOUNCE",
    "air_date": "2010-07-06",
    "question": "'In this kid's game, you bounce a small rubber ball while picking up 6-pronged metal objects'",
    "value": "$600",
    "answer": "jacks",
    "round": "Jeopardy!",
    "show_number": "5957"
  },
  {
    "category": "RHYMES WITH SMART",
    "air_date": "2010-07-06",
    "question": "'It can be a separating line in your hair or a role in a play'",
    "value": "$600",
    "answer": "a part",
    "round": "Jeopardy!",
    "show_number": "5957"
  },
  {
    "category": "GEOGRAPHY \"E\"",
    "air_date": "2010-07-06",
    "question": "'Parts of the Arabian and Libyan deserts are found in this African country'",
    "value": "$800",
    "answer": "Egypt",
    "round": "Jeopardy!",
    "show_number": "5957"
  },
  {
    "category": "RADIO DISNEY",
    "air_date": "2010-07-06",
    "question": "'\"I Never Told You\" this alliteratively named singer hit Disney's Top 30 with \"Fallin' For You\"; wait, I just did'",
    "value": "$800",
    "answer": "Colbie Caillat",
    "round": "Jeopardy!",
    "show_number": "5957"
  },
  {
    "category": "PARTS OF PEACH",
    "air_date": "2010-07-06",
    "question": "'These parts of a peach tree are glossy green, pointed & lance shaped'",
    "value": "$800",
    "answer": "leaves",
    "round": "Jeopardy!",
    "show_number": "5957"
  },
  {
    "category": "BE FRUITFUL & MULTIPLY",
    "air_date": "2010-07-06",
    "question": "'5 x 10 x 15'",
    "value": "$800",
    "answer": "750",
    "round": "Jeopardy!",
    "show_number": "5957"
  },
  {
    "category": "LET'S BOUNCE",
    "air_date": "2010-07-06",
    "question": "'It's a type of bounce house, or a dance made famous by Michael Jackson'",
    "value": "$800",
    "answer": "the moonwalk",
    "round": "Jeopardy!",
    "show_number": "5957"
  },
  {
    "category": "RHYMES WITH SMART",
    "air_date": "2010-07-06",
    "question": "'A graphic representation of information'",
    "value": "$800",
    "answer": "a chart",
    "round": "Jeopardy!",
    "show_number": "5957"
  },
  {
    "category": "GEOGRAPHY \"E\"",
    "air_date": "2010-07-06",
    "question": "'The family history you wrote for school might include entering the U.S. at this island in New York Bay'",
    "value": "$2,000",
    "answer": "Ellis Island",
    "round": "Jeopardy!",
    "show_number": "5957"
  },
  {
    "category": "RADIO DISNEY",
    "air_date": "2010-07-06",
    "question": "'Lead singer Ryan Tedder of this band has \"All The Right Moves\"'",
    "value": "$1000",
    "answer": "OneRepublic",
    "round": "Jeopardy!",
    "show_number": "5957"
  },
  {
    "category": "PARTS OF PEACH",
    "air_date": "2010-07-06",
    "question": "'These parts of a peach tree grow at nodes along the shoots of the previous season's growth; they're usually pink'",
    "value": "$1000",
    "answer": "blossoms",
    "round": "Jeopardy!",
    "show_number": "5957"
  },
  {
    "category": "BE FRUITFUL & MULTIPLY",
    "air_date": "2010-07-06",
    "question": "'2 x 1,035'",
    "value": "$1000",
    "answer": "2,070",
    "round": "Jeopardy!",
    "show_number": "5957"
  },
  {
    "category": "LET'S BOUNCE",
    "air_date": "2010-07-06",
    "question": "'This device whose name is from the Italian for \"springboard\" was perfected in the 1930s'",
    "value": "$1000",
    "answer": "a trampoline",
    "round": "Jeopardy!",
    "show_number": "5957"
  },
  {
    "category": "RHYMES WITH SMART",
    "air_date": "2010-07-06",
    "question": "'Composer Wolfgang'",
    "value": "$1000",
    "answer": "Mozart",
    "round": "Jeopardy!",
    "show_number": "5957"
  },
  {
    "category": "SCIENCE CLASS",
    "air_date": "2010-07-06",
    "question": "'99.95% of the mass of an atom is in this part'",
    "value": "$400",
    "answer": "the nucleus",
    "round": "Double Jeopardy!",
    "show_number": "5957"
  },
  {
    "category": "KIDS IN SPORTS",
    "air_date": "2010-07-06",
    "question": "'Park View of Chula Vista, California beat Taipei 6-3 to win this organization's 2009 World Series'",
    "value": "$400",
    "answer": "the Little League",
    "round": "Double Jeopardy!",
    "show_number": "5957"
  },
  {
    "category": "JUST THE FACTS",
    "air_date": "2010-07-06",
    "question": "'This hero of several books is 11 when he discovers he's a wizard'",
    "value": "$400",
    "answer": "Harry Potter",
    "round": "Double Jeopardy!",
    "show_number": "5957"
  },
  {
    "category": "SEE & SAY",
    "air_date": "2010-07-06",
    "question": "'Say the name of <a href=\"http://www.j-archive.com/media/2010-07-06_DJ_26.jpg\" target=\"_blank\">this</a> type of mollusk you see'",
    "value": "$400",
    "answer": "an octopus",
    "round": "Double Jeopardy!",
    "show_number": "5957"
  },
  {
    "category": "NEWS TO ME",
    "air_date": "2010-07-06",
    "question": "'A 7.0 magnitude earthquake in this Caribbean country Jan. 12, 2010 brought a world outpouring of aid'",
    "value": "$400",
    "answer": "Haiti",
    "round": "Double Jeopardy!",
    "show_number": "5957"
  },
  {
    "category": "IN THE DICTIONARY",
    "air_date": "2010-07-06",
    "question": "'It's the 4-letter name of the pleated skirt worn by men in Scotland'",
    "value": "$400",
    "answer": "a kilt",
    "round": "Double Jeopardy!",
    "show_number": "5957"
  },
  {
    "category": "SCIENCE CLASS",
    "air_date": "2010-07-06",
    "question": "'During this plant process, carbon dioxide & water combine with light energy to create oxygen & glucose'",
    "value": "$800",
    "answer": "photosynthesis",
    "round": "Double Jeopardy!",
    "show_number": "5957"
  },
  {
    "category": "KIDS IN SPORTS",
    "air_date": "2010-07-06",
    "question": "'The perfect waves of New Zealand's Piha Beach were the site for the 2010 World Junior Championships of this'",
    "value": "$800",
    "answer": "surfing",
    "round": "Double Jeopardy!",
    "show_number": "5957"
  },
  {
    "category": "JUST THE FACTS",
    "air_date": "2010-07-06",
    "question": "'This city, the seat of Clark County, Nevada, has been called \"the entertainment capital of the world\"'",
    "value": "$800",
    "answer": "Las Vegas",
    "round": "Double Jeopardy!",
    "show_number": "5957"
  },
  {
    "category": "SEE & SAY",
    "air_date": "2010-07-06",
    "question": "'Say <a href=\"http://www.j-archive.com/media/2010-07-06_DJ_27.jpg\" target=\"_blank\">this</a> state that was admitted to the Union in 1859'",
    "value": "$800",
    "answer": "Oregon",
    "round": "Double Jeopardy!",
    "show_number": "5957"
  },
  {
    "category": "NEWS TO ME",
    "air_date": "2010-07-06",
    "question": "'This car company has been in the news for widespread recalls of its Corollas & other models'",
    "value": "$800",
    "answer": "Toyota",
    "round": "Double Jeopardy!",
    "show_number": "5957"
  },
  {
    "category": "IN THE DICTIONARY",
    "air_date": "2010-07-06",
    "question": "'As an adjective, it can mean proper; as a verb, \"to grade papers\"'",
    "value": "$800",
    "answer": "correct",
    "round": "Double Jeopardy!",
    "show_number": "5957"
  },
  {
    "category": "SCIENCE CLASS",
    "air_date": "2010-07-06",
    "question": "'The wedge is an adaptation of the simple machine called the inclined this'",
    "value": "$1200",
    "answer": "plane",
    "round": "Double Jeopardy!",
    "show_number": "5957"
  },
  {
    "category": "KIDS IN SPORTS",
    "air_date": "2010-07-06",
    "question": "'With a mighty leap of 5'1\", David Mosely set the U.S. 10 & under record in this event back in 1977'",
    "value": "$1200",
    "answer": "the high jump",
    "round": "Double Jeopardy!",
    "show_number": "5957"
  },
  {
    "category": "JUST THE FACTS",
    "air_date": "2010-07-06",
    "question": "'<a href=\"http://www.j-archive.com/media/2010-07-06_DJ_14.jpg\" target=\"_blank\">This dog breed seen here</a> is a loyal and protective companion'",
    "value": "$1200",
    "answer": "a German Shepherd",
    "round": "Double Jeopardy!",
    "show_number": "5957"
  },
  {
    "category": "SEE & SAY",
    "air_date": "2010-07-06",
    "question": "'Say the name of <a href=\"http://www.j-archive.com/media/2010-07-06_DJ_28.jpg\" target=\"_blank\">this</a> bug; don't worry, it doesn't breathe fire'",
    "value": "$1200",
    "answer": "the dragonfly",
    "round": "Double Jeopardy!",
    "show_number": "5957"
  },
  {
    "category": "NEWS TO ME",
    "air_date": "2010-07-06",
    "question": "'(<a href=\"http://www.j-archive.com/media/2010-07-06_DJ_21.wmv\">Jimmy of the Clue Crew demonstrates, putting his arm over his mouth.</a>) To avoid spreading germs & maybe flu, we learned the sneeze named for this character made famous in an 1897 book'",
    "value": "$1200",
    "answer": "Dracula",
    "round": "Double Jeopardy!",
    "show_number": "5957"
  },
  {
    "category": "IN THE DICTIONARY",
    "air_date": "2010-07-06",
    "question": "'Maize is another word for this'",
    "value": "$1200",
    "answer": "corn",
    "round": "Double Jeopardy!",
    "show_number": "5957"
  },
  {
    "category": "SCIENCE CLASS",
    "air_date": "2010-07-06",
    "question": "'Of the 6 noble gases on the periodic table, it is the lightest'",
    "value": "$5,000",
    "answer": "helium",
    "round": "Double Jeopardy!",
    "show_number": "5957"
  },
  {
    "category": "KIDS IN SPORTS",
    "air_date": "2010-07-06",
    "question": "'11-year-old Ashlyn White won a 2009 U.S. youth title in this martial art in which you try to throw your opponent'",
    "value": "$1600",
    "answer": "judo",
    "round": "Double Jeopardy!",
    "show_number": "5957"
  },
  {
    "category": "JUST THE FACTS",
    "air_date": "2010-07-06",
    "question": "'In 1751 the Penn Provincial Assembly placed the order for this symbol of freedom, now in Philadelphia'",
    "value": "$1600",
    "answer": "the Liberty Bell",
    "round": "Double Jeopardy!",
    "show_number": "5957"
  },
  {
    "category": "SEE & SAY",
    "air_date": "2010-07-06",
    "question": "'Say the name of <a href=\"http://www.j-archive.com/media/2010-07-06_DJ_29.jpg\" target=\"_blank\">these</a> big trees; it has a color in it'",
    "value": "$1600",
    "answer": "redwood",
    "round": "Double Jeopardy!",
    "show_number": "5957"
  },
  {
    "category": "NEWS TO ME",
    "air_date": "2010-07-06",
    "question": "'In a surprise, Ted Kennedy's old Senate seat in this state went to a Republican in a January 2010 election'",
    "value": "$1600",
    "answer": "Massachusetts",
    "round": "Double Jeopardy!",
    "show_number": "5957"
  },
  {
    "category": "IN THE DICTIONARY",
    "air_date": "2010-07-06",
    "question": "'This word for someone who walks comes from the Latin for \"foot\"'",
    "value": "$5,000",
    "answer": "pedestrian",
    "round": "Double Jeopardy!",
    "show_number": "5957"
  },
  {
    "category": "SCIENCE CLASS",
    "air_date": "2010-07-06",
    "question": "'Lava & igneous rock are formed from this hot liquid rock material found under the earth's crust'",
    "value": "$2000",
    "answer": "magma",
    "round": "Double Jeopardy!",
    "show_number": "5957"
  },
  {
    "category": "KIDS IN SPORTS",
    "air_date": "2010-07-06",
    "question": "'This sport has an under-17 World Cup every 2 years; Haris Seferovic starred for the 2009 champion Switzerland'",
    "value": "$2000",
    "answer": "soccer",
    "round": "Double Jeopardy!",
    "show_number": "5957"
  },
  {
    "category": "JUST THE FACTS",
    "air_date": "2010-07-06",
    "question": "'He's the older son of Prince Charles and the late Princess Diana'",
    "value": "$2000",
    "answer": "Prince William",
    "round": "Double Jeopardy!",
    "show_number": "5957"
  },
  {
    "category": "SEE & SAY",
    "air_date": "2010-07-06",
    "question": "'Say the name of <a href=\"http://www.j-archive.com/media/2010-07-06_DJ_30.jpg\" target=\"_blank\">this</a> man you see shaking hands with the Premier of China'",
    "value": "$2000",
    "answer": "Ronald Reagan",
    "round": "Double Jeopardy!",
    "show_number": "5957"
  },
  {
    "category": "NEWS TO ME",
    "air_date": "2010-07-06",
    "question": "'Falcon Heene, who it turned out was safe at home, not flying over Colorado, became known as this \"boy\"'",
    "value": "$2000",
    "answer": "the balloon boy",
    "round": "Double Jeopardy!",
    "show_number": "5957"
  },
  {
    "category": "IN THE DICTIONARY",
    "air_date": "2010-07-06",
    "question": "'Kayak is an example of this, a word that reads the same forwards & backwards'",
    "value": "$2000",
    "answer": "a palindrome",
    "round": "Double Jeopardy!",
    "show_number": "5957"
  }
]
